setup.py
number_game/__init__.py
number_game/game.py
number_game.egg-info/PKG-INFO
number_game.egg-info/SOURCES.txt
number_game.egg-info/dependency_links.txt
number_game.egg-info/top_level.txt