Metadata-Version: 1.1
Name: number-game
Version: 0.0.1
Summary: A number game to play
Home-page: https://github.com/pypa/sampleproject
Author: Fidan Musazade
Author-email: frmusazade@gmail.com
License: UNKNOWN
Platform: UNKNOWN
Classifier: Programming Language :: Python :: 3
Classifier: License :: OSI Approved :: MIT License
Classifier: Operating System :: OS Independent
